u64-0.3.0.dist-info/METADATA
u64-0.3.0.dist-info/WHEEL
u64-0.3.0.dist-info/licenses/LICENSE
u64/__init__.py
u64/__init__.pyi
u64/py.typed
u64/u64.cp39-win_amd64.pyd
u64-0.3.0.dist-info/RECORD
