Metadata-Version: 2.4
Name: u64
Version: 0.3.0
Classifier: Development Status :: 4 - Beta
Classifier: License :: OSI Approved :: MIT License
Classifier: Programming Language :: Rust
Classifier: Programming Language :: Python :: Implementation :: CPython
Classifier: Programming Language :: Python :: Implementation :: PyPy
License-File: LICENSE
Summary: A fast unsigned 64-bit integer type
Requires-Python: >=3.8
Project-URL: repository, https://github.com/thealtofwar/u64
